clock_pattern/__init__.py
clock_pattern/py.typed
clock_pattern/clocks/__init__.py
clock_pattern/clocks/system_clock.py
clock_pattern/clocks/utc_clock.py
clock_pattern/clocks/testing/__init__.py
clock_pattern/clocks/testing/fixed_clock.py
clock_pattern/clocks/testing/mock_clock.py
clock_pattern/models/__init__.py
clock_pattern/models/clock.py
clock_pattern-0.5.0.dist-info/METADATA
clock_pattern-0.5.0.dist-info/WHEEL
clock_pattern-0.5.0.dist-info/licenses/LICENSE.md
clock_pattern-0.5.0.dist-info/RECORD
