Metadata-Version: 2.4
Name: clock-pattern
Version: 0.5.0
Summary: The Clock Pattern is a Python package that turns time into an injectable dependency.
Project-URL: Homepage, https://github.com/adriamontoto/clock-pattern
Project-URL: Repository, https://github.com/adriamontoto/clock-pattern
Project-URL: Issues, https://github.com/adriamontoto/clock-pattern/issues
Author: Adria Montoto
License-Expression: MIT
License-File: LICENSE.md
Keywords: clock,dependency-injection,development,domain-driven-design,pattern,python,utilities
Classifier: Intended Audience :: Developers
Classifier: License :: OSI Approved :: MIT License
Classifier: Operating System :: OS Independent
Classifier: Programming Language :: Python
Classifier: Programming Language :: Python :: 3
Classifier: Programming Language :: Python :: 3.11
Classifier: Programming Language :: Python :: 3.12
Classifier: Programming Language :: Python :: 3.13
Classifier: Typing :: Typed
Requires-Python: >=3.11
Requires-Dist: value-object-pattern>=0.6.0
